{"id":798275,"name":"Build a responsive website using HTML5 & CSS3","slug":"html5-css3-bootstrap-build-a-responsive-website","subtitle":null,"product_id":838944,"description":"From creating your first html file to advanced skills with forms, text, navigation & Bootstrap 4, this in-depth course will transform your skill set & equip you with techniques to start building your professional sites with HTML & CSS3 confidently.","intro_video_youtube":null,"contact_information":null,"keywords":null,"duration":null,"banner_image_url":"/assets/tenant/default-course-banner.jpg","course_card_image_url":"https://import.cdn.thinkific.com/114242/u0yMPa4TxaY61lwIJLo7_Untitled%20design%20%2815%29-min.jpg","intro_video_wistia_identifier":null,"administrator_user_ids":[],"user_id":6359966,"reviews_enabled":true,"instructor_id":153181,"chapter_ids":[3722213,3722218,3722214,3722217,3722220,3745296,3698690],"course_card_text":null}